[
  {
    "title": "\n\n            \n            Flat Oude Vest 109\n\n                            \n"
  },
  {
    "address": "\n                2312 XV Leiden (Marewijk)\n            "
  },
  {
    "title": "\n\n            \n            House Anna Maria van Schuurmanstraat\n\n                            \n"
  },
  {
    "address": "\n                2331 DC Leiden (Schenkwijk)\n            "
  },
  {
    "title": "\n\n            \n            Flat Rapenburg\n\n                            \n"
  },
  {
    "address": "\n                2311 EZ Leiden (Pieterswijk)\n            "
  }
]